freq_note_converter/__init__.py
freq_note_converter/converter_code.py
freq_note_converter_tests/__init__.py
freq_note_converter_tests/test___init__.py
freq_note_converter-0.2.0.dist-info/LICENSE
freq_note_converter-0.2.0.dist-info/METADATA
freq_note_converter-0.2.0.dist-info/WHEEL
freq_note_converter-0.2.0.dist-info/top_level.txt
freq_note_converter-0.2.0.dist-info/RECORD
