Metadata-Version: 2.1
Name: freq-note-converter
Version: 0.2.0
Summary: convert notes to freq and vise verse
Home-page: https://github.com/lisrael1/freq_note_converter
Author: Lior Israeli
Author-email: israelilior@gmail.com
License: UNKNOWN
Project-URL: Bug Tracker, https://github.com/lisrael1/freq_note_converter/issues
Platform: UNKNOWN
Classifier: Programming Language :: Python :: 3
Classifier: License :: OSI Approved :: MIT License
Classifier: Operating System :: OS Independent
Requires-Python: >=3.6
License-File: LICENSE
Requires-Dist: dict-aligned-print
